oList/__init__.py
oList-0.0.3.dist-info/METADATA
oList-0.0.3.dist-info/WHEEL
oList-0.0.3.dist-info/top_level.txt
oList-0.0.3.dist-info/RECORD
