Metadata-Version: 2.1
Name: oList
Version: 0.0.3
Summary: A Python 'Object List'. It's basically your standard python list that additionally lets you attach data to it that doesn't affect the actual list items itself.
Home-page: https://github.com/mwd1993/oList
Author: Marc D
Author-email: marcwarrelldavis@yahoo.com
License: UNKNOWN
Platform: UNKNOWN
Classifier: Programming Language :: Python :: 3
Classifier: License :: OSI Approved :: MIT License
Classifier: Operating System :: OS Independent
Requires-Python: >=3.6
